drb/signatures/xquery.py
drb/xquery/XQueryLexer.py
drb/xquery/XQueryParser.py
drb/xquery/XQueryParserListener.py
drb/xquery/XQueryParserVisitor.py
drb/xquery/__init__.py
drb/xquery/_version.py
drb/xquery/drb_xquery.py
drb/xquery/drb_xquery_cmd.py
drb/xquery/drb_xquery_context.py
drb/xquery/drb_xquery_func.py
drb/xquery/drb_xquery_item.py
drb/xquery/drb_xquery_res_to_string.py
drb/xquery/drb_xquery_utils.py
drb/xquery/drb_xquery_variable.py
drb/xquery/drb_xquery_visitor.py
drb/xquery/execptions.py
drb_xquery-1.3.0.dist-info/LICENCE.txt
drb_xquery-1.3.0.dist-info/METADATA
drb_xquery-1.3.0.dist-info/WHEEL
drb_xquery-1.3.0.dist-info/entry_points.txt
drb_xquery-1.3.0.dist-info/top_level.txt
drb_xquery-1.3.0.dist-info/RECORD
