Metadata-Version: 2.1
Name: drb-xquery
Version: 1.3.0
Summary: DRB xquery request
Author: GAEL Systems
Author-email: drb-python@gael.fr
License: LGPLv3
Classifier: Programming Language :: Python :: 3.8
Classifier: License :: OSI Approved :: GNU Lesser General Public License v3 (LGPLv3)
Requires-Python: >=3.8
License-File: LICENCE.txt
Requires-Dist: drb ~=2.2.0
Requires-Dist: antlr4-python3-runtime ==4.9.3
Requires-Dist: python-dateutil ~=2.8.2
Requires-Dist: Click
